ipvc
