Metadata-Version: 1.0
Name: ipvc
Version: 0.1.2
Summary: Inter-Planetary Version Control (System)
Home-page: https://github.com/rememberberry/ipvc
Author: Martin Pettersson
Author-email: martin@rememberberry.com
License: UNKNOWN
Platform: UNKNOWN
